.gitignore
CHANGELOG.rst
LICENSE.txt
README.md
demo.gif
example.ipynb
pyproject.toml
tox.ini
uv.lock
.github/workflows/sdist.yml
.github/workflows/tox.yml
src/obi_notebook/__init__.py
src/obi_notebook/get_entities.py
src/obi_notebook/get_environment.py
src/obi_notebook/get_projects.py
src/obi_notebook.egg-info/PKG-INFO
src/obi_notebook.egg-info/SOURCES.txt
src/obi_notebook.egg-info/dependency_links.txt
src/obi_notebook.egg-info/requires.txt
src/obi_notebook.egg-info/top_level.txt